azure_extras/__init__.py
azure_extras/asctl.py
azure_extras/healthchkctl.py
azure_extras/kuductl.py
azure_extras/sajctl.py
azure_extras/lib/__init__.py
azure_extras/lib/app.py
azure_extras/lib/az.py
azure_extras/lib/kudu.py
azure_extras/lib/saj.py
azure_extras/lib/utils.py
azure_extras-0.3.1.dist-info/LICENSE
azure_extras-0.3.1.dist-info/METADATA
azure_extras-0.3.1.dist-info/WHEEL
azure_extras-0.3.1.dist-info/entry_points.txt
azure_extras-0.3.1.dist-info/top_level.txt
azure_extras-0.3.1.dist-info/RECORD
