Metadata-Version: 2.1
Name: azure-extras
Version: 0.3.1
Summary: The stuff Microsoft left out..
Home-page: https://gitlab.com/tslight/azure_extras
Author: Toby Slight
Author-email: tslight@pm.me
Classifier: Programming Language :: Python :: 3
Classifier: License :: OSI Approved :: ISC License (ISCL)
Classifier: Operating System :: OS Independent
License-File: LICENSE
Requires-Dist: azure-common
Requires-Dist: azure-cli-core
Requires-Dist: msrest
Requires-Dist: msrestazure
Requires-Dist: requests
